{
    "Series": "NASCAR Sprint Cup Series",
    "Order": "01",
    "Circuit": "Daytona International Speedway - USA",
    "Event": "Premier",
    "Weather": "Clear",
    "Lap Record": "1:00.00 - 2010 - Driver (Team)",
    "Qualifying Results": [
        {
            "Position": 1,
            "Driver": "J. P. Montoya",
            "Team": "#42 - Earnhardt Ganassi Racing",
            "Supplier": "Chevrolet",
            "Sponsor": "Target",
            "Time": "0:37.75"
        },
        {
            "Position": 2,
            "Driver": "J. Gordon",
            "Team": "#24 - Hendrick Motorsports",
            "Supplier": "Chevrolet",
            "Sponsor": "DuPont",
            "Time": "0:37.83"
        },
        {
            "Position": 3,
            "Driver": "B. Keselowski",
            "Team": "#12 - Penske Championship Racing",
            "Supplier": "Dodge",
            "Sponsor": "Verizon",
            "Time": "0:38.15"
        },
        {
            "Position": 4,
            "Driver": "M. Martin",
            "Team": "#5  - Hendrick Motorsports",
            "Supplier": "Chevrolet",
            "Sponsor": "GoDaddy",
            "Time": "0:38.32"
        },
        {
            "Position": 5,
            "Driver": "G. Biffle",
            "Team": "#16 - Roush Fenway Racing",
            "Supplier": "Ford",
            "Sponsor": "3M",
            "Time": "0:38.56"
        },
        {
            "Position": 6,
            "Driver": "J. Johnson",
            "Team": "#48 - Hendrick Motorsports",
            "Supplier": "Chevrolet",
            "Sponsor": "Lowe's",
            "Time": "0:38.78"
        },
        {
            "Position": 7,
            "Driver": "R. Newman",
            "Team": "#39 - Stewart-Haas Racing",
            "Supplier": "Chevrolet",
            "Sponsor": "U.S. Army",
            "Time": "0:38.87"
        },
        {
            "Position": 8,
            "Driver": "D. Hamlin",
            "Team": "#11 - Joe Gibbs Racing",
            "Supplier": "Toyota",
            "Sponsor": "FedEx",
            "Time": "0:38.94"
        },
        {
            "Position": 9,
            "Driver": "M. Ambrose",
            "Team": "#47 - JTG Daugherty Racing",
            "Supplier": "Toyota",
            "Sponsor": "Kroger",
            "Time": "0:38.94"
        },
        {
            "Position": 10,
            "Driver": "J. Logano",
            "Team": "#20 - Joe Gibbs Racing",
            "Supplier": "Toyota",
            "Sponsor": "The Home Depot",
            "Time": "0:38.97"
        },
        {
            "Position": 11,
            "Driver": "Ky. Busch",
            "Team": "#18 - Joe Gibbs Racing",
            "Supplier": "Toyota",
            "Sponsor": "M&M's",
            "Time": "0:39.04"
        },
        {
            "Position": 12,
            "Driver": "J. Burton",
            "Team": "#31 - Richard Childress Racing",
            "Supplier": "Chevrolet",
            "Sponsor": "Caterpillar",
            "Time": "0:39.39"
        },
        {
            "Position": 13,
            "Driver": "D. Reutimann",
            "Team": "#00 - Michael Waltrip Racing",
            "Supplier": "Toyota",
            "Sponsor": "Aaron's",
            "Time": "0:39.42"
        },
        {
            "Position": 14,
            "Driver": "M. Truex Jr.",
            "Team": "#56 - Michael Waltrip Racing",
            "Supplier": "Toyota",
            "Sponsor": "NAPA",
            "Time": "0:39.43"
        },
        {
            "Position": 15,
            "Driver": "D. Earnhardt Jr.",
            "Team": "#88 - Hendrick Motorsports",
            "Supplier": "Chevrolet",
            "Sponsor": "Mountain Dew",
            "Time": "0:39.44"
        },
        {
            "Position": 16,
            "Driver": "J. Nemechek",
            "Team": "#87 - NEMCO Motorsports",
            "Supplier": "Toyota",
            "Sponsor": "",
            "Time": "0:39.59"
        },
        {
            "Position": 17,
            "Driver": "C. Edwards",
            "Team": "#99 - Roush Fenway Racing",
            "Supplier": "Ford",
            "Sponsor": "Aflac",
            "Time": "0:39.67"
        },
        {
            "Position": 18,
            "Driver": "S. Hornish Jr.",
            "Team": "#77 - Penske Championship Racing",
            "Supplier": "Dodge",
            "Sponsor": "Mobil 1",
            "Time": "0:39.80"
        },
        {
            "Position": 19,
            "Driver": "B. Labonte",
            "Team": "#71 - The Racer's Group Motorsports",
            "Supplier": "Chevrolet",
            "Sponsor": "TaxSlayer",
            "Time": "0:39.87"
        },
        {
            "Position": 20,
            "Driver": "S. Speed",
            "Team": "#82 - Red Bull Racing Team",
            "Supplier": "Toyota",
            "Sponsor": "Red Bull",
            "Time": "0:39.97"
        },
        {
            "Position": 21,
            "Driver": "T. Kvapil",
            "Team": "#37 - Front Row Motorsports",
            "Supplier": "Ford",
            "Sponsor": "ExtenZe",
            "Time": "0:40.14"
        },
        {
            "Position": 22,
            "Driver": "P. Menard",
            "Team": "#98 - Richard Petty Motorsports",
            "Supplier": "Ford",
            "Sponsor": "Menards",
            "Time": "0:40.23"
        },
        {
            "Position": 23,
            "Driver": "K. Kahne",
            "Team": "#9  - Richard Petty Motorsports",
            "Supplier": "Ford",
            "Sponsor": "Budweiser",
            "Time": "0:40.54"
        },
        {
            "Position": 24,
            "Driver": "R. Gordon",
            "Team": "#7  - Robby Gordon Motorsports",
            "Supplier": "Toyota",
            "Sponsor": "Monster Energy",
            "Time": "0:40.57"
        },
        {
            "Position": 25,
            "Driver": "K. Busch",
            "Team": "#2  - Penske Championship Racing",
            "Supplier": "Dodge",
            "Sponsor": "Miller Lite",
            "Time": "0:40.57"
        },
        {
            "Position": 26,
            "Driver": "K. Harvick",
            "Team": "#29 - Richard Childress Racing",
            "Supplier": "Chevrolet",
            "Sponsor": "Pennzoil",
            "Time": "0:40.61"
        },
        {
            "Position": 27,
            "Driver": "M. Waltrip",
            "Team": "#51 - Michael Waltrip Racing",
            "Supplier": "Toyota",
            "Sponsor": "NAPA Auto Parts",
            "Time": "0:40.65"
        },
        {
            "Position": 28,
            "Driver": "T. Stewart",
            "Team": "#14 - Stewart-Haas Racing",
            "Supplier": "Chevrolet",
            "Sponsor": "Office Depot",
            "Time": "0:40.72"
        },
        {
            "Position": 29,
            "Driver": "J. McMurray",
            "Team": "#1  - Earnhardt Ganassi Racing",
            "Supplier": "Chevrolet",
            "Sponsor": "Bass Pro Shops",
            "Time": "0:41.18"
        },
        {
            "Position": 30,
            "Driver": "R. Sorenson",
            "Team": "#32 - Braun Racing",
            "Supplier": "Toyota",
            "Sponsor": "Dollar General",
            "Time": "0:41.26"
        },
        {
            "Position": 31,
            "Driver": "T. Raines",
            "Team": "#64 - Gunselman Motorsports",
            "Supplier": "Toyota",
            "Sponsor": "",
            "Time": "0:41.28"
        },
        {
            "Position": 32,
            "Driver": "R. Richardson Jr.",
            "Team": "#38 - Front Row Motorsports",
            "Supplier": "Ford",
            "Sponsor": "Mahindra Tractors",
            "Time": "0:41.29"
        },
        {
            "Position": 33,
            "Driver": "J. Andretti",
            "Team": "#34 - Front Row Motorsports",
            "Supplier": "Ford",
            "Sponsor": "Window World",
            "Time": "0:41.37"
        },
        {
            "Position": 34,
            "Driver": "R. Smith",
            "Team": "#78 - Furniture Row Racing",
            "Supplier": "Chevrolet",
            "Sponsor": "Furniture Row",
            "Time": "0:41.41"
        },
        {
            "Position": 35,
            "Driver": "C. Bowyer",
            "Team": "#33 - Richard Childress Racing",
            "Supplier": "Chevrolet",
            "Sponsor": "Cheerios",
            "Time": "0:41.43"
        },
        {
            "Position": 36,
            "Driver": "M. Kenseth",
            "Team": "#17 - Roush Fenway Racing",
            "Supplier": "Ford",
            "Sponsor": "Crown Royal",
            "Time": "0:41.53"
        },
        {
            "Position": 37,
            "Driver": "D. Ragan",
            "Team": "#6  - Roush Fenway Racing",
            "Supplier": "Ford",
            "Sponsor": "UPS",
            "Time": "0:42.07"
        },
        {
            "Position": 38,
            "Driver": "B. Vickers",
            "Team": "#83 - Red Bull Racing Team",
            "Supplier": "Toyota",
            "Sponsor": "Red Bull",
            "Time": "0:42.08"
        },
        {
            "Position": 39,
            "Driver": "D. Gilliand",
            "Team": "#49 - BAM Racing",
            "Supplier": "Toyota",
            "Sponsor": "Warner Brothers",
            "Time": "0:42.19"
        },
        {
            "Position": 40,
            "Driver": "B. Elliott",
            "Team": "#21 - Wood Brothers Racing",
            "Supplier": "Ford",
            "Sponsor": "Motorcraft",
            "Time": "0:42.30"
        },
        {
            "Position": 41,
            "Driver": "E. Sadler",
            "Team": "#19 - Richard Petty Motorsports",
            "Supplier": "Ford",
            "Sponsor": "Stanley Tools",
            "Time": "0:42.59"
        },
        {
            "Position": 42,
            "Driver": "A. J. Allmendinger",
            "Team": "#43 - Richard Petty Motorsports",
            "Supplier": "Ford",
            "Sponsor": "Best Buy",
            "Time": "0:42.92"
        },
        {
            "Position": 43,
            "Driver": "B. Said",
            "Team": "#26 - Latitude 43 Motorsports",
            "Supplier": "Ford",
            "Sponsor": "Window World",
            "Time": "0:44.32"
        }
    ],
    "DNQ Drivers": [
        {
            "Position": 44,
            "Driver": "J. Fuller",
            "Team": "#97 - NEMCO Motorsports",
            "Supplier": "Toyota",
            "Sponsor": "FrontRowJoe",
            "Time": "0:42.31"
        },
        {
            "Position": 45,
            "Driver": "T. Cook",
            "Team": "#46 - Whitney Motorsports",
            "Supplier": "Dodge",
            "Sponsor": "",
            "Time": "0:42.50"
        },
        {
            "Position": 46,
            "Driver": "C. Mears",
            "Team": "#90 - Keyed-Up Motorsports",
            "Supplier": "Chevrolet",
            "Sponsor": "",
            "Time": "0:42.56"
        },
        {
            "Position": 47,
            "Driver": "M. Wallace",
            "Team": "#92 - K-Automotive Motorsports",
            "Supplier": "Dodge",
            "Sponsor": "",
            "Time": "0:42.85"
        },
        {
            "Position": 48,
            "Driver": "A. Almirola",
            "Team": "#09 - Phoenix Racing",
            "Supplier": "Chevrolet",
            "Sponsor": "",
            "Time": "0:43.41"
        },
        {
            "Position": 49,
            "Driver": "M. Bliss",
            "Team": "#36 - Tommy Baldwin Racing",
            "Supplier": "Chevrolet",
            "Sponsor": "Wave Energy",
            "Time": "0:43.59"
        },
        {
            "Position": 50,
            "Driver": "M. Papis",
            "Team": "#13 - Germain Racing",
            "Supplier": "Toyota",
            "Sponsor": "GEICO",
            "Time": "0:43.71"
        },
        {
            "Position": 51,
            "Driver": "D. Blaney",
            "Team": "#66 - Prism Motorsports",
            "Supplier": "Toyota",
            "Sponsor": "",
            "Time": "0:43.76"
        },
        {
            "Position": 52,
            "Driver": "M. McDowell",
            "Team": "#55 - Prism Motorsports",
            "Supplier": "Toyota",
            "Sponsor": "",
            "Time": "0:44.78"
        },
        {
            "Position": 53,
            "Driver": "N. Benning",
            "Team": "#57 - Norm Benning Racing",
            "Supplier": "Chevrolet",
            "Sponsor": "",
            "Time": "0:45.34"
        },
        {
            "Position": 54,
            "Driver": "D. Cope",
            "Team": "#75 - Stratus Racing Group",
            "Supplier": "Dodge",
            "Sponsor": "StrutmastersPro",
            "Time": "0:45.80"
        }
    ],
    "Race Results": [
        {
            "Position": 1,
            "Driver": "G. Biffle",
            "Team": "#16 - Roush Fenway Racing",
            "Supplier": "Ford",
            "Sponsor": "3M",
            "Time": "128:53.29"
        },
        {
            "Position": 2,
            "Driver": "Ky. Busch",
            "Team": "#18 - Joe Gibbs Racing",
            "Supplier": "Toyota",
            "Sponsor": "M&M's",
            "Time": "130:30.73"
        },
        {
            "Position": 3,
            "Driver": "J. P. Montoya",
            "Team": "#42 - Earnhardt Ganassi Racing",
            "Supplier": "Chevrolet",
            "Sponsor": "Target",
            "Time": "130:50.35"
        },
        {
            "Position": 4,
            "Driver": "D. Hamlin",
            "Team": "#11 - Joe Gibbs Racing",
            "Supplier": "Toyota",
            "Sponsor": "FedEx",
            "Time": "134:49.56"
        },
        {
            "Position": 5,
            "Driver": "J. Johnson",
            "Team": "#48 - Hendrick Motorsports",
            "Supplier": "Chevrolet",
            "Sponsor": "Lowe's",
            "Time": "135:30.21"
        },
        {
            "Position": 6,
            "Driver": "J. Gordon",
            "Team": "#24 - Hendrick Motorsports",
            "Supplier": "Chevrolet",
            "Sponsor": "DuPont",
            "Time": "137:59.84"
        },
        {
            "Position": 7,
            "Driver": "M. Martin",
            "Team": "#5  - Hendrick Motorsports",
            "Supplier": "Chevrolet",
            "Sponsor": "GoDaddy",
            "Time": "139:02.59"
        },
        {
            "Position": 8,
            "Driver": "M. Ambrose",
            "Team": "#47 - JTG Daugherty Racing",
            "Supplier": "Toyota",
            "Sponsor": "Kroger",
            "Time": "139:52.75"
        },
        {
            "Position": 9,
            "Driver": "K. Harvick",
            "Team": "#29 - Richard Childress Racing",
            "Supplier": "Chevrolet",
            "Sponsor": "Pennzoil",
            "Time": "140:27.38"
        },
        {
            "Position": 10,
            "Driver": "R. Newman",
            "Team": "#39 - Stewart-Haas Racing",
            "Supplier": "Chevrolet",
            "Sponsor": "U.S. Army",
            "Time": "141:22.32"
        },
        {
            "Position": 11,
            "Driver": "T. Kvapil",
            "Team": "#37 - Front Row Motorsports",
            "Supplier": "Ford",
            "Sponsor": "ExtenZe",
            "Time": "141:47.47"
        },
        {
            "Position": 12,
            "Driver": "P. Menard",
            "Team": "#98 - Richard Petty Motorsports",
            "Supplier": "Ford",
            "Sponsor": "Menards",
            "Time": "142:25.16"
        },
        {
            "Position": 13,
            "Driver": "C. Edwards",
            "Team": "#99 - Roush Fenway Racing",
            "Supplier": "Ford",
            "Sponsor": "Aflac",
            "Time": "142:58.08"
        },
        {
            "Position": 14,
            "Driver": "M. Kenseth",
            "Team": "#17 - Roush Fenway Racing",
            "Supplier": "Ford",
            "Sponsor": "Crown Royal",
            "Time": "143:12.97"
        },
        {
            "Position": 15,
            "Driver": "B. Keselowski",
            "Team": "#12 - Penske Championship Racing",
            "Supplier": "Dodge",
            "Sponsor": "Verizon",
            "Time": "143:33.28"
        },
        {
            "Position": 16,
            "Driver": "S. Speed",
            "Team": "#82 - Red Bull Racing Team",
            "Supplier": "Toyota",
            "Sponsor": "Red Bull",
            "Time": "143:57.88"
        },
        {
            "Position": 17,
            "Driver": "J. Burton",
            "Team": "#31 - Richard Childress Racing",
            "Supplier": "Chevrolet",
            "Sponsor": "Caterpillar",
            "Time": "144:37.15"
        },
        {
            "Position": 18,
            "Driver": "J. Logano",
            "Team": "#20 - Joe Gibbs Racing",
            "Supplier": "Toyota",
            "Sponsor": "The Home Depot",
            "Time": "144:49.89"
        },
        {
            "Position": 19,
            "Driver": "D. Earnhardt Jr.",
            "Team": "#88 - Hendrick Motorsports",
            "Supplier": "Chevrolet",
            "Sponsor": "Mountain Dew",
            "Time": "147:38.89"
        },
        {
            "Position": 20,
            "Driver": "T. Stewart",
            "Team": "#14 - Stewart-Haas Racing",
            "Supplier": "Chevrolet",
            "Sponsor": "Office Depot",
            "Time": "149:11.65"
        },
        {
            "Position": 21,
            "Driver": "J. McMurray",
            "Team": "#1  - Earnhardt Ganassi Racing",
            "Supplier": "Chevrolet",
            "Sponsor": "Bass Pro Shops",
            "Time": "151:07.28"
        },
        {
            "Position": 22,
            "Driver": "B. Labonte",
            "Team": "#71 - The Racer's Group Motorsports",
            "Supplier": "Chevrolet",
            "Sponsor": "TaxSlayer",
            "Time": "153:53.13"
        },
        {
            "Position": 23,
            "Driver": "S. Hornish Jr.",
            "Team": "#77 - Penske Championship Racing",
            "Supplier": "Dodge",
            "Sponsor": "Mobil 1",
            "Time": "154:20.21"
        },
        {
            "Position": 24,
            "Driver": "J. Nemechek",
            "Team": "#87 - NEMCO Motorsports",
            "Supplier": "Toyota",
            "Sponsor": "",
            "Time": "156:23.05"
        },
        {
            "Position": 25,
            "Driver": "M. Waltrip",
            "Team": "#51 - Michael Waltrip Racing",
            "Supplier": "Toyota",
            "Sponsor": "NAPA Auto Parts",
            "Time": "156:33.25"
        },
        {
            "Position": 26,
            "Driver": "A. J. Allmendinger",
            "Team": "#43 - Richard Petty Motorsports",
            "Supplier": "Ford",
            "Sponsor": "Best Buy",
            "Time": "159:47.76"
        },
        {
            "Position": 27,
            "Driver": "D. Ragan",
            "Team": "#6  - Roush Fenway Racing",
            "Supplier": "Ford",
            "Sponsor": "UPS",
            "Time": "160:19.41"
        },
        {
            "Position": 28,
            "Driver": "J. Andretti",
            "Team": "#34 - Front Row Motorsports",
            "Supplier": "Ford",
            "Sponsor": "Window World",
            "Time": "161:15.58"
        },
        {
            "Position": 29,
            "Driver": "D. Gilliand",
            "Team": "#49 - BAM Racing",
            "Supplier": "Toyota",
            "Sponsor": "Warner Brothers",
            "Time": "161:48.20"
        },
        {
            "Position": 30,
            "Driver": "R. Richardson Jr.",
            "Team": "#38 - Front Row Motorsports",
            "Supplier": "Ford",
            "Sponsor": "Mahindra Tractors",
            "Time": "166:40.00"
        },
        {
            "Position": 31,
            "Driver": "E. Sadler",
            "Team": "#19 - Richard Petty Motorsports",
            "Supplier": "Ford",
            "Sponsor": "Stanley Tools",
            "Time": "166:40.00"
        },
        {
            "Position": 32,
            "Driver": "B. Said",
            "Team": "#26 - Latitude 43 Motorsports",
            "Supplier": "Ford",
            "Sponsor": "Window World",
            "Time": "166:40.00"
        }
    ],
    "DNF Drivers": [
        {
            "Position": "DNF",
            "Driver": "D. Reutimann",
            "Team": "#00 - Michael Waltrip Racing",
            "Supplier": "Toyota",
            "Sponsor": "Aaron's",
            "Reason": "Collision"
        },
        {
            "Position": "DNF",
            "Driver": "M. Truex Jr.",
            "Team": "#56 - Michael Waltrip Racing",
            "Supplier": "Toyota",
            "Sponsor": "NAPA",
            "Reason": "Collision"
        },
        {
            "Position": "DNF",
            "Driver": "K. Kahne",
            "Team": "#9  - Richard Petty Motorsports",
            "Supplier": "Ford",
            "Sponsor": "Budweiser",
            "Reason": "Collision"
        },
        {
            "Position": "DNF",
            "Driver": "R. Gordon",
            "Team": "#7  - Robby Gordon Motorsports",
            "Supplier": "Toyota",
            "Sponsor": "Monster Energy",
            "Reason": "Collision"
        },
        {
            "Position": "DNF",
            "Driver": "K. Busch",
            "Team": "#2  - Penske Championship Racing",
            "Supplier": "Dodge",
            "Sponsor": "Miller Lite",
            "Reason": "Retirement"
        },
        {
            "Position": "DNF",
            "Driver": "R. Sorenson",
            "Team": "#32 - Braun Racing",
            "Supplier": "Toyota",
            "Sponsor": "Dollar General",
            "Reason": "Retirement"
        },
        {
            "Position": "DNF",
            "Driver": "T. Raines",
            "Team": "#64 - Gunselman Motorsports",
            "Supplier": "Toyota",
            "Sponsor": "",
            "Reason": "Retirement"
        },
        {
            "Position": "DNF",
            "Driver": "R. Smith",
            "Team": "#78 - Furniture Row Racing",
            "Supplier": "Chevrolet",
            "Sponsor": "Furniture Row",
            "Reason": "Retirement"
        },
        {
            "Position": "DNF",
            "Driver": "C. Bowyer",
            "Team": "#33 - Richard Childress Racing",
            "Supplier": "Chevrolet",
            "Sponsor": "Cheerios",
            "Reason": "Collision"
        },
        {
            "Position": "DNF",
            "Driver": "B. Vickers",
            "Team": "#83 - Red Bull Racing Team",
            "Supplier": "Toyota",
            "Sponsor": "Red Bull",
            "Reason": "Collision"
        },
        {
            "Position": "DNF",
            "Driver": "B. Elliott",
            "Team": "#21 - Wood Brothers Racing",
            "Supplier": "Ford",
            "Sponsor": "Motorcraft",
            "Reason": "Crash"
        }
    ],
    "Fastest Lap": {
        "Driver": "J. P. Montoya",
        "Time": "0:42.63"
    },
    "Most Laps Led": {
        "Driver": "D. Hamlin",
        "Laps": 92
    }
}